{
  "resourceType": "CarePlan",
  "id": "cpvCar8",
  "author": [
    {
      "reference": "Practitioner/cpvPra4"
    }
  ],
  "subject": {
    "reference": "Patient/cpvPat2"
  },
  "status": "active",
  "period": {
    "start": "2016-10-12", //TODO
    "end": "2016-11-24"
  },
  "addresses": [
    {
      "reference": "cpvCon7"
    }
  ],
  "goal": //TODO
  "description": "CP description",
  "text": {
    "status": "generated",
    "div": "<div xmlns=\"http://www.w3.org/1999/xhtml\"><p>Template 1</p></div>"
  },
  "activity": [
    {
      "reference": //TODO
    },
    {
      "reference": //TODO
    },
    {
      "reference": //TODO
    },
    {
      "reference": //TODO
    },
    {
      "reference": //TODO
    },
    {
      "reference": //TODO
    }
  ]
}